[
    {
        "id": "de6ddbb7-8d9e-45b4-85e9-2de6de30d77f",
        "name": "Mushrooms - Honey",
        "unit": "$8.90"
    },
    {
        "id": "8c74c686-7f7c-4d31-8f0f-a8344f2261cc",
        "name": "Wine - Barbera Alba Doc 2001",
        "unit": "$8.75"
    },
    {
        "id": "a3d4f82c-8954-413a-aab3-c13d4e1d377b",
        "name": "Nestea - Ice Tea, Diet",
        "unit": "$9.30"
    },
    {
        "id": "3ecdf5b0-6a96-4644-abd8-d2d654b0dff9",
        "name": "Cake - Mini Potato Pancake",
        "unit": "$3.61"
    },
    {
        "id": "237d3934-d965-41fc-9dd8-13a4b497184f",
        "name": "Tomatoes - Orange",
        "unit": "$9.89"
    },
    {
        "id": "247a5081-0fe2-455b-947f-9092e0038001",
        "name": "Pop Shoppe Cream Soda",
        "unit": "$3.13"
    },
    {
        "id": "1fea4acc-86d3-4e8a-9a14-a2967a49d86c",
        "name": "Garbage Bags - Clear",
        "unit": "$6.15"
    },
    {
        "id": "13005170-ed60-457e-a2b4-2f63374d9478",
        "name": "Steel Wool",
        "unit": "$6.56"
    },
    {
        "id": "b4edeef4-74c9-4c60-97da-251f2b2e121d",
        "name": "Sun - Dried Tomatoes",
        "unit": "$2.66"
    },
    {
        "id": "7213419e-4a53-49a0-a383-a1886a0efdd9",
        "name": "Lamb - Whole Head Off",
        "unit": "$3.96"
    },
    {
        "id": "40fd7621-dd05-4dd6-b4b3-c4cdb2fc775a",
        "name": "Puree - Pear",
        "unit": "$2.74"
    },
    {
        "id": "78c26115-1ed6-4c7c-a9a3-05355334041c",
        "name": "Juice - Propel Sport",
        "unit": "$0.08"
    },
    {
        "id": "f9fb19fe-a20d-424e-ab2e-9904340e4e70",
        "name": "Pastry - Carrot Muffin - Mini",
        "unit": "$3.00"
    },
    {
        "id": "c731bbd7-c372-4188-b4d3-efbc88f0a5d9",
        "name": "Milk - Homo",
        "unit": "$5.33"
    },
    {
        "id": "e9c70755-3eaf-46f3-8041-c10ecac94fb7",
        "name": "Cookies - Oreo, 4 Pack",
        "unit": "$3.92"
    },
    {
        "id": "f00b8a10-6cb7-46f3-90df-b6faf119e188",
        "name": "Smirnoff Green Apple Twist",
        "unit": "$5.50"
    },
    {
        "id": "83a849f6-a084-475c-abfe-8b3625007f81",
        "name": "Wine - Pinot Noir Mondavi Coastal",
        "unit": "$4.58"
    },
    {
        "id": "15977982-04b5-45ae-8be2-c2a8d57d5957",
        "name": "Fish - Halibut, Cold Smoked",
        "unit": "$0.10"
    },
    {
        "id": "d20ea5d8-93ae-4c0e-95fd-8d109f26d775",
        "name": "Wine - Carmenere Casillero Del",
        "unit": "$1.06"
    },
    {
        "id": "ef9606f7-3e3e-471a-b31c-8830f61e8710",
        "name": "Wine - Niagara Peninsula Vqa",
        "unit": "$8.29"
    },
    {
        "id": "3144e449-87ba-49b5-b0c9-d78dcffb6968",
        "name": "Beans - Fine",
        "unit": "$7.27"
    },
    {
        "id": "822138e2-763e-49ce-bee7-ccd0bd7bb0cd",
        "name": "Lettuce - Romaine, Heart",
        "unit": "$4.98"
    },
    {
        "id": "c82a751d-ad1c-4106-ba94-9019ad8acaf6",
        "name": "Syrup - Monin, Swiss Choclate",
        "unit": "$4.51"
    },
    {
        "id": "992d0458-40f1-4c66-9b24-05c1b898ff57",
        "name": "Cake - Miini Cheesecake Cherry",
        "unit": "$1.57"
    },
    {
        "id": "7d09743b-0644-498a-94d7-6fc85df0a68e",
        "name": "Oregano - Dry, Rubbed",
        "unit": "$2.53"
    },
    {
        "id": "901d94d8-757d-498c-8c78-12b9327033dd",
        "name": "Mountain Dew",
        "unit": "$2.83"
    },
    {
        "id": "e7f5768d-4292-43c2-8f4f-753d52794349",
        "name": "Cheese - Manchego, Spanish",
        "unit": "$3.84"
    },
    {
        "id": "fbae1d17-b5cd-4b13-87e2-24330ce06291",
        "name": "Syrup - Golden, Lyles",
        "unit": "$4.41"
    },
    {
        "id": "84db357a-d944-4b4b-8afc-49e03c68b00d",
        "name": "Wine - Magnotta - Belpaese",
        "unit": "$9.31"
    },
    {
        "id": "8231bd10-4695-4364-aa7c-cd7dc6e24309",
        "name": "Beef - Kindney, Whole",
        "unit": "$7.90"
    }
]